django_admin_magic/__init__.py
django_admin_magic/admin.py
django_admin_magic/apps.py
django_admin_magic/conf.py
django_admin_magic/defaults.py
django_admin_magic/mixins.py
django_admin_magic/registrar.py
django_admin_magic/utils.py
django_admin_magic-0.1.9.dist-info/METADATA
django_admin_magic-0.1.9.dist-info/WHEEL
django_admin_magic-0.1.9.dist-info/top_level.txt
django_admin_magic-0.1.9.dist-info/RECORD
